version_finder_cli/__init__.py
version_finder_cli/__version__.py
version_finder_cli/cli.py
version_finder_git_based_versions_cli-2.1.1.dist-info/LICENSE
version_finder_git_based_versions_cli-2.1.1.dist-info/METADATA
version_finder_git_based_versions_cli-2.1.1.dist-info/WHEEL
version_finder_git_based_versions_cli-2.1.1.dist-info/entry_points.txt
version_finder_git_based_versions_cli-2.1.1.dist-info/top_level.txt
version_finder_git_based_versions_cli-2.1.1.dist-info/RECORD
