Metadata-Version: 2.2
Name: version-finder-git-based-versions-cli
Version: 2.1.1
Summary: A utility for finding versions in Git repositories
Home-page: https://github.com/LevyMatan/version_finder
Author: Matan Levy
License: MIT
Classifier: Programming Language :: Python :: 3
Classifier: License :: OSI Approved :: MIT License
Classifier: Operating System :: OS Independent
Requires-Python: >=3.7
License-File: LICENSE
Requires-Dist: version-finder-git-based-versions>=7.0.1
Requires-Dist: prompt_toolkit>=3.0.0
Provides-Extra: dev
Requires-Dist: pytest; extra == "dev"
Requires-Dist: pytest-xdist; extra == "dev"
Requires-Dist: pytest-cov; extra == "dev"
Requires-Dist: flake8; extra == "dev"
Requires-Dist: autopep8; extra == "dev"
Dynamic: author
Dynamic: classifier
Dynamic: description
Dynamic: description-content-type
Dynamic: home-page
Dynamic: license
Dynamic: provides-extra
Dynamic: requires-dist
Dynamic: requires-python
Dynamic: summary
